docs/AGENT_GUIDE.md
docs/BEST_PRACTICES.md
docs/BOOTSTRAP_GUIDE.md
docuchango/__init__.py
docuchango/__main__.py
docuchango/cli.py
docuchango/schemas.py
docuchango/validator.py
docuchango/fixes/__init__.py
docuchango/fixes/broken_links.py
docuchango/fixes/code_blocks.py
docuchango/fixes/code_blocks_proper.py
docuchango/fixes/cross_plugin_links.py
docuchango/fixes/doc_links.py
docuchango/fixes/docs.py
docuchango/fixes/internal_links.py
docuchango/fixes/mdx_code_blocks.py
docuchango/fixes/mdx_syntax.py
docuchango/fixes/migration_syntax.py
docuchango/fixes/proto_imports.py
docuchango/templates/README.md
docuchango/templates/adr-000-template.md
docuchango/templates/docs-project.yaml
docuchango/templates/memo-000-template.md
docuchango/templates/prd-000-template.md
docuchango/templates/rfc-000-template.md
examples/README.md
examples/docs-cms/docs-project.yaml
examples/docs-cms/fix_frontmatter.sh
examples/docs-cms/adr/adr-001-adopt-docs-cms.md
examples/docs-cms/adr/adr-002-agent-collaboration-workflow.md
examples/docs-cms/memos/memo-001-docs-cms-launch.md
examples/docs-cms/rfcs/rfc-001-automated-doc-generation.md
examples/docs-cms/templates/adr-template.md
examples/docs-cms/templates/memo-template.md
examples/docs-cms/templates/rfc-template.md
templates/README.md
templates/adr-template.md
templates/frd-template.md
templates/generic-doc-template.md
templates/memo-template.md
templates/prd-template.md
templates/prdfaq-template.md
templates/rfc-template.md
docuchango-1.3.6.dist-info/METADATA
docuchango-1.3.6.dist-info/WHEEL
docuchango-1.3.6.dist-info/entry_points.txt
docuchango-1.3.6.dist-info/licenses/LICENSE
docuchango-1.3.6.dist-info/RECORD
