Metadata-Version: 2.4
Name: docuchango
Version: 1.3.6
Summary: Docusaurus validation and repair framework for opinionated micro-CMS documentation, designed for human-agent collaboration workflows
Project-URL: Homepage, https://github.com/jrepp/docuchango
Project-URL: Documentation, https://github.com/jrepp/docuchango#readme
Project-URL: Repository, https://github.com/jrepp/docuchango
Project-URL: Issues, https://github.com/jrepp/docuchango/issues
Author-email: Jacob Repp <jacobrepp@gmail.com>
License: MPL-2.0
License-File: LICENSE
Keywords: cli,cms,collaboration,documentation,docusaurus,markdown,validation
Classifier: Development Status :: 4 - Beta
Classifier: Intended Audience :: Developers
Classifier: License :: OSI Approved
Classifier: Programming Language :: Python :: 3
Classifier: Programming Language :: Python :: 3.9
Classifier: Programming Language :: Python :: 3.10
Classifier: Programming Language :: Python :: 3.11
Classifier: Programming Language :: Python :: 3.12
Classifier: Programming Language :: Python :: 3.13
Classifier: Topic :: Documentation
Classifier: Topic :: Software Development :: Quality Assurance
Classifier: Topic :: Software Development :: Testing
Requires-Python: >=3.9
Requires-Dist: click>=8.0.0
Requires-Dist: eval-type-backport>=0.2.0; python_version < '3.10'
Requires-Dist: pydantic>=2.0.0
Requires-Dist: python-frontmatter>=1.0.0
Requires-Dist: pyyaml>=6.0
Requires-Dist: rich>=13.0.0
Provides-Extra: dev
Requires-Dist: mypy>=1.0.0; extra == 'dev'
Requires-Dist: pytest-cov>=5.0.0; extra == 'dev'
Requires-Dist: pytest-timeout>=2.0.0; extra == 'dev'
Requires-Dist: pytest-xdist>=3.0.0; extra == 'dev'
Requires-Dist: pytest>=8.0.0; extra == 'dev'
Requires-Dist: ruff>=0.1.0; extra == 'dev'
Requires-Dist: types-pyyaml>=6.0.0; extra == 'dev'
Provides-Extra: lint
Requires-Dist: mypy>=1.0.0; extra == 'lint'
Requires-Dist: ruff>=0.1.0; extra == 'lint'
Requires-Dist: types-pyyaml>=6.0.0; extra == 'lint'
Provides-Extra: test
Requires-Dist: pytest-cov>=5.0.0; extra == 'test'
Requires-Dist: pytest-timeout>=2.0.0; extra == 'test'
Requires-Dist: pytest-xdist>=3.0.0; extra == 'test'
Requires-Dist: pytest>=8.0.0; extra == 'test'
